unicode_string_literal.py
unicode_string_literal-1.0.1.dist-info/DESCRIPTION.rst
unicode_string_literal-1.0.1.dist-info/entry_points.txt
unicode_string_literal-1.0.1.dist-info/METADATA
unicode_string_literal-1.0.1.dist-info/metadata.json
unicode_string_literal-1.0.1.dist-info/RECORD
unicode_string_literal-1.0.1.dist-info/top_level.txt
unicode_string_literal-1.0.1.dist-info/WHEEL
