Metadata-Version: 2.0
Name: unicode-string-literal
Version: 1.0.1
Summary: Flake8 String Literal Enforcer Extension
Home-page: https://github.com/cogniteev/flake8-unicode-string-literal.git
Author: Cogniteev
Author-email: tech@cogniteev.com
License: Apache license 2.0
Download-URL: https://github.com/cogniteev/flake8-unicode-string-literal/tarball/v1.0.1
Keywords: flake8 unicode string
Platform: UNKNOWN
Requires-Dist: setuptools
